jobhunting/__init__.py
jobhunting/config.py
jobhunting/credentails.py
jobhunting/Models/Infojobs.py
jobhunting/Models/__init__.py
jobhunting/Models/apinfo.py
jobhunting/Models/vagasCom.py
jobhunting/const/__init__.py
jobhunting/controllers/apinfoController.py
jobhunting/controllers/infojobsController.py
jobhunting/controllers/vagasComController.py
jobhunting/utils/__init__.py
jobhunting/utils/errors.py
jobhunting/utils/load_txt.py
jobhunting/utils/output.py
jobhunting/utils/sanitize.py
jobhunting/utils/sanitize_input.py
jobhunting/utils/selenium_path.py
job_hunting-0.2.18.dist-info/METADATA
job_hunting-0.2.18.dist-info/WHEEL
job_hunting-0.2.18.dist-info/top_level.txt
job_hunting-0.2.18.dist-info/RECORD
