Metadata-Version: 2.1
Name: job-hunting
Version: 0.2.18
Summary: Package that automate selection and subscription of jobs
Home-page: https://job-hunting.readthedocs.io/
Author: Jeferson/MxJeff
Author-email: mx.jeferson.10@hotmail.com
License: UNKNOWN
Platform: UNKNOWN
Classifier: Intended Audience :: Developers
Classifier: License :: OSI Approved :: MIT License
Classifier: Programming Language :: Python
Classifier: Programming Language :: Python :: 3
Classifier: Programming Language :: Python :: 3.6
Classifier: Programming Language :: Python :: 3.7
Classifier: Programming Language :: Python :: 3.8
Classifier: Programming Language :: Python :: 3.9
Classifier: Operating System :: OS Independent
Requires-Dist: selenium
Requires-Dist: python-dotenv
Requires-Dist: scrapper-boilerplate
